{"cameraMode":{"drawMode":0,"name":"Shaded","section":"Shading Mode"},"sceneLighting":false,"audioPlay":false,"sceneViewState":{"m_AlwaysRefresh":false,"showFog":true,"showSkybox":false,"showFlares":true,"showImageEffects":true,"showParticleSystems":true,"showVisualEffectGraphs":true,"m_FxEnabled":true},"in2DMode":false,"pivot":{"x":0.0,"y":0.014980808831751347,"z":0.0},"rotation":{"x":0.6643106341362,"y":0.22802555561065675,"z":-0.22417590022087098,"w":0.675550103187561},"size":0.0913579910993576,"orthographic":false}